[
    {
        "id": 1,
        "nome": "Laiane",
        "idade": 26,
        "telefone": "81992043480",
        "cpf": ""
    },
    {
        "id": 2,
        "nome": "Michelli",
        "idade": 42,
        "telefone": "891234543",
        "cpf": "028379283"
    },
    {
        "id": 3,
        "nome": "Augusto",
        "idade": 12,
        "telefone": "129483902",
        "cpf": "2938479204"
    },
    {
        "id": 4,
        "nome": "Joana Maria",
        "idade": 24,
        "telefone": "124839993",
        "cpf": "198382940932"
    }
]